LICENSE
MANIFEST.in
README.rst
setup.cfg
setup.py
tox.ini
img/example.png
sphinxcontrib/__init__.py
sphinxcontrib/cqlengine/__init__.py
sphinxcontrib_cqlengine.egg-info/PKG-INFO
sphinxcontrib_cqlengine.egg-info/SOURCES.txt
sphinxcontrib_cqlengine.egg-info/dependency_links.txt
sphinxcontrib_cqlengine.egg-info/namespace_packages.txt
sphinxcontrib_cqlengine.egg-info/not-zip-safe
sphinxcontrib_cqlengine.egg-info/requires.txt
sphinxcontrib_cqlengine.egg-info/top_level.txt