Metadata-Version: 1.1
Name: sphinxcontrib-cqlengine
Version: 0.1
Summary: Sphinx "cqlengine" extension
Home-page: https://github.com/dokai/sphinxcontrib-cqlengine
Author: Kai Lautaportti
Author-email: kai.lautaportti@gmail.com
License: BSD
Download-URL: http://pypi.python.org/pypi/sphinxcontrib-cqlengine
Platform: any
Classifier: Development Status :: 4 - Beta
Classifier: Environment :: Console
Classifier: Environment :: Web Environment
Classifier: Intended Audience :: Developers
Classifier: License :: OSI Approved :: BSD License
Classifier: Operating System :: OS Independent
Classifier: Programming Language :: Python
Classifier: Topic :: Documentation
Classifier: Topic :: Utilities
